disputils/__init__.py
disputils/abc.py
disputils/confirmation.py
disputils/multiple_choice.py
disputils/pagination.py
disputils-0.2.0.dist-info/LICENSE
disputils-0.2.0.dist-info/METADATA
disputils-0.2.0.dist-info/WHEEL
disputils-0.2.0.dist-info/top_level.txt
disputils-0.2.0.dist-info/RECORD
