Metadata-Version: 2.1
Name: disputils
Version: 0.2.0
Summary: Some utilities for discord.py. Making Discord bot development easier.
Home-page: https://github.com/LiBa001/disputils
Author: Linus Bartsch
Author-email: linus.pypi@mabasoft.de
License: MIT
Keywords: discord discord-py discord-bot utils utility
Platform: UNKNOWN
Classifier: License :: OSI Approved :: MIT License
Classifier: Programming Language :: Python :: 3.6
Requires-Python: >=3.6
